{
  "intents": [
    {
      "tag": "greeting",
      "patterns": [
        "Hi","Hey","Hello","How are you","Is anyone there?","Good day",
        "Moin"
      ],
      "responses": [
        "Hey :)", "Hello","Hello, thanks for visiting",
        "Hi, how can I help you?","Hi, what can I do for you?"
      ]
    },
    {
      "tag": "good bye",
      "patterns": ["bye", "goodbye","see you later"],
      "responses": [
        "see you later, thanks for visiting",
        "Have a nice day",
        "goodbye! Come back again"
      ]
    },
    {
      "tag": "thanks",
      "patterns": ["thanks","thank you","That's helpful","Thanks a lot!"],
      "responses": [
        "Happy to help!", "Any Time", "My pleasure"
      ]
    },
    {
      "tag": "menu",
      "patterns": [
        "do you have a menu?",
        "what all pizzas do you have?",
        "what is on the menu?"
      ],
      "responses": [
       "We have Margerita, Salami, Tuna, Vegan and veggi delight"
      ]
    },
    {
      "tag": "toppings",
      "patterns": [
        "what all toppings do you have?",
        "can I add extra toppings?",
        "can i add toppings?",
        "what about toppings?"
      ],
      "responses": [
        "We can add cheese, jalepenos, onions, chilli flakes, pineapple. Toppings cost 50 cent extra for each"
      ]
    },
    {
      "tag": "drinks",
      "patterns": [
        "Do you have coke?",
        "do you have pepsi?",
        "do you have fanta?",
        "do you have any cool drinks?",
        "any drinks available?"
      ],
      "responses": [
        "We have Coke, Fanta and Pepsi"
      ]
    },
    {
      "tag": "payments",
      "patterns": [
        "Do you take credit card?",
        "Can I pay you cash?",
        "Do you accept paypal",
        "Can I pay with Mastercard?"
      ],
      "responses": [
        "We accept all kinds of payment - VISA, Cash, Mastercard, Paypal and Bitcoin"
      ]
    },
    {
      "tag": "delivery",
      "patterns": [
        "How long does the delivery take?",
        "How long does the shipping take?",
        "when do I get my delivery?"
      ],
      "responses": [
        "Delivery takes half an hour",
        "Delivery takes thirty minutes"
      ]
    }
  ]
}